{
  "request": {
    "checkpoint_version": 1,
    "revision": "d8d48d17cc6f92c84b2108a198024db05bb17e65",
    "artifact": "mame-linux-clang-d8d48d17cc6f92c84b2108a198024db05bb17e65",
    "variant": "previous",
    "input_fingerprint": "b3650a301c4f8f056a51854d5b5297fef33dbd13cc43dbade8a660501b0e48a9"
  },
  "result": {
    "name": "dash_a37b",
    "status": "failed",
    "button": "1 Player Start",
    "revision": "d8d48d17cc6f92c84b2108a198024db05bb17e65",
    "captures": {
      "previous": {
        "status": "failed",
        "captured_at": "2026-07-21T17:36:37.097552+00:00",
        "duration_seconds": 1.655,
        "button": "1 Player Start",
        "button_applied": true,
        "warmup_seconds": 30.0,
        "after_seconds": 2.0,
        "press_seconds": 0.25,
        "failure_reason": "Fatal error: Required files are missing, the machine cannot be run.",
        "revision": "d8d48d17cc6f92c84b2108a198024db05bb17e65",
        "artifact": "mame-linux-clang-d8d48d17cc6f92c84b2108a198024db05bb17e65"
      }
    }
  }
}
