{
  "request": {
    "checkpoint_version": 1,
    "revision": "ff317eaf2d304aa0456a1df93915624489cb7aae",
    "artifact": "mame-linux-clang-ff317eaf2d304aa0456a1df93915624489cb7aae",
    "variant": "previous",
    "input_fingerprint": "73a150d8d4f5048923f10e7424de07d1848d69ada973498900481a0769e44cca"
  },
  "result": {
    "name": "ax80",
    "status": "failed",
    "button": "1 Player Start",
    "revision": "ff317eaf2d304aa0456a1df93915624489cb7aae",
    "captures": {
      "previous": {
        "status": "failed",
        "captured_at": "2026-07-21T23:27:20.316902+00:00",
        "duration_seconds": 1.634,
        "button": "1 Player Start",
        "button_applied": false,
        "warmup_seconds": 30.0,
        "after_seconds": 2.0,
        "press_seconds": 0.25,
        "failure_reason": "machine has no emulated screen",
        "revision": "ff317eaf2d304aa0456a1df93915624489cb7aae",
        "artifact": "mame-linux-clang-ff317eaf2d304aa0456a1df93915624489cb7aae"
      }
    }
  }
}
