{
  "request": {
    "checkpoint_version": 1,
    "revision": "b937c2e7fa50ff4e74386d2cf071382b2f37af4b",
    "artifact": "mame-linux-clang-b937c2e7fa50ff4e74386d2cf071382b2f37af4b",
    "variant": "previous",
    "input_fingerprint": "3d74950f26ccc71a9b28436e6938a2281780aa526cd93a8c8c7302ba1846d35f"
  },
  "result": {
    "name": "pokegach",
    "status": "failed",
    "button": "1 Player Start",
    "revision": "b937c2e7fa50ff4e74386d2cf071382b2f37af4b",
    "captures": {
      "previous": {
        "status": "failed",
        "captured_at": "2026-07-21T22:19:42.080837+00:00",
        "duration_seconds": 1.106,
        "button": "1 Player Start",
        "button_applied": true,
        "warmup_seconds": 30.0,
        "after_seconds": 2.0,
        "press_seconds": 0.25,
        "failure_reason": "Fatal error: Required files are missing, the machine cannot be run.",
        "revision": "b937c2e7fa50ff4e74386d2cf071382b2f37af4b",
        "artifact": "mame-linux-clang-b937c2e7fa50ff4e74386d2cf071382b2f37af4b"
      }
    }
  }
}
