{
  "request": {
    "checkpoint_version": 1,
    "revision": "fc93524e3b8037c66ee3b56018b9a2531906df3f",
    "artifact": "mame-linux-clang-fc93524e3b8037c66ee3b56018b9a2531906df3f",
    "variant": "current",
    "input_fingerprint": "3d14d2167d1af36022ec348e4f1b7e6074e55902e6bcff9e8c0af380a2ae99ba"
  },
  "result": {
    "name": "grid1109",
    "status": "failed",
    "button": "1 Player Start",
    "revision": "fc93524e3b8037c66ee3b56018b9a2531906df3f",
    "captures": {
      "current": {
        "status": "failed",
        "captured_at": "2026-07-21T17:56:52.691844+00:00",
        "duration_seconds": 0.711,
        "button": "1 Player Start",
        "button_applied": true,
        "warmup_seconds": 30.0,
        "after_seconds": 2.0,
        "press_seconds": 0.25,
        "failure_reason": "Fatal error: Images must be mounted for the following devices: bubble",
        "revision": "fc93524e3b8037c66ee3b56018b9a2531906df3f",
        "artifact": "mame-linux-clang-fc93524e3b8037c66ee3b56018b9a2531906df3f"
      }
    }
  }
}
