{
  "request": {
    "checkpoint_version": 1,
    "revision": "6e05adef683297f82359f1400db677a6095779d0",
    "artifact": "mame-linux-clang-6e05adef683297f82359f1400db677a6095779d0",
    "variant": "current",
    "input_fingerprint": "93fbd33abdf25728ee84726f289e2359300030ba67972faf59040b42ec8cf04f"
  },
  "result": {
    "name": "t250",
    "status": "failed",
    "button": "1 Player Start",
    "revision": "6e05adef683297f82359f1400db677a6095779d0",
    "captures": {
      "current": {
        "status": "failed",
        "captured_at": "2026-07-21T16:32:14.576511+00:00",
        "duration_seconds": 1.073,
        "button": "1 Player Start",
        "button_applied": true,
        "warmup_seconds": 30.0,
        "after_seconds": 2.0,
        "press_seconds": 0.25,
        "failure_reason": "Fatal error: Required files are missing, the machine cannot be run.",
        "revision": "6e05adef683297f82359f1400db677a6095779d0",
        "artifact": "mame-linux-clang-6e05adef683297f82359f1400db677a6095779d0"
      }
    }
  }
}
